pydt_utils/__init__.py
pydt_utils/anomaly.py
pydt_utils/brazing.py
pydt_utils/cycle.py
pydt_utils/plot.py
pydt_utils/thermal.py
pydt_utils-0.1.1.dist-info/licenses/LICENSE
pydt_utils-0.1.1.dist-info/METADATA
pydt_utils-0.1.1.dist-info/WHEEL
pydt_utils-0.1.1.dist-info/top_level.txt
pydt_utils-0.1.1.dist-info/RECORD
