Metadata-Version: 2.4
Name: pydt-utils
Version: 0.1.1
Summary: Thermal cycle analysis, validation
Author-email: Vishwa A <vishwa7890@gmail.com>
License-Expression: MIT
Project-URL: Homepage, https://github.com/vishwa7890/pydt-utils
Project-URL: Documentation, https://github.com/vishwa7890/pydt-utils#readme
Project-URL: Repository, https://github.com/vishwa7890/pydt-utils
Project-URL: Issues, https://github.com/vishwa7890/pydt-utils/issues
Keywords: digital-twin,brazing,thermal-analysis,simulation,anomaly-detection
Classifier: Development Status :: 3 - Alpha
Classifier: Intended Audience :: Science/Research
Classifier: Intended Audience :: Manufacturing
Classifier: Programming Language :: Python :: 3
Classifier: Programming Language :: Python :: 3.8
Classifier: Programming Language :: Python :: 3.9
Classifier: Programming Language :: Python :: 3.10
Classifier: Programming Language :: Python :: 3.11
Classifier: Topic :: Scientific/Engineering
Classifier: Topic :: Scientific/Engineering :: Physics
Requires-Python: >=3.8
License-File: LICENSE
Requires-Dist: numpy>=1.20.0
Requires-Dist: scipy>=1.7.0
Requires-Dist: matplotlib>=3.4.0
Provides-Extra: dev
Requires-Dist: pytest>=7.0.0; extra == "dev"
Requires-Dist: pytest-cov>=3.0.0; extra == "dev"
Requires-Dist: black>=22.0.0; extra == "dev"
Requires-Dist: flake8>=4.0.0; extra == "dev"
Dynamic: license-file
